[
  {
    "ContainingType": "APIBanXeDap.Controllers.AccountsController",
    "Method": "checkCCCD",
    "RelativePath": "api/Accounts/checkCCCD",
    "HttpMethod": "GET",
    "IsController": true,
    "Order": 0,
    "Parameters": [
      {
        "Name": "cccd",
        "Type": "System.String",
        "IsRequired": false
      }
    ],
    "ReturnTypes": []
  },
  {
    "ContainingType": "APIBanXeDap.Controllers.AccountsController",
    "Method": "checkEmail",
    "RelativePath": "api/Accounts/checkEmail",
    "HttpMethod": "GET",
    "IsController": true,
    "Order": 0,
    "Parameters": [
      {
        "Name": "email",
        "Type": "System.String",
        "IsRequired": false
      }
    ],
    "ReturnTypes": []
  },
  {
    "ContainingType": "APIBanXeDap.Controllers.AccountsController",
    "Method": "checkUsername",
    "RelativePath": "api/Accounts/checkUsername",
    "HttpMethod": "GET",
    "IsController": true,
    "Order": 0,
    "Parameters": [
      {
        "Name": "username",
        "Type": "System.String",
        "IsRequired": false
      }
    ],
    "ReturnTypes": []
  },
  {
    "ContainingType": "APIBanXeDap.Controllers.AccountsController",
    "Method": "ForgotPasswordCustomer",
    "RelativePath": "api/Accounts/ForgotPasswordCustomer",
    "HttpMethod": "GET",
    "IsController": true,
    "Order": 0,
    "Parameters": [
      {
        "Name": "email",
        "Type": "System.String",
        "IsRequired": false
      }
    ],
    "ReturnTypes": []
  },
  {
    "ContainingType": "APIBanXeDap.Controllers.AccountsController",
    "Method": "ForgotPasswordStaff",
    "RelativePath": "api/Accounts/ForgotPasswordStaff",
    "HttpMethod": "GET",
    "IsController": true,
    "Order": 0,
    "Parameters": [
      {
        "Name": "email",
        "Type": "System.String",
        "IsRequired": false
      }
    ],
    "ReturnTypes": []
  },
  {
    "ContainingType": "APIBanXeDap.Controllers.AccountsController",
    "Method": "GoogleResponse",
    "RelativePath": "api/Accounts/GoogleResponse",
    "HttpMethod": "GET",
    "IsController": true,
    "Order": 0,
    "Parameters": [],
    "ReturnTypes": []
  },
  {
    "ContainingType": "APIBanXeDap.Controllers.AccountsController",
    "Method": "LoginCustomer",
    "RelativePath": "api/Accounts/LoginCustomer",
    "HttpMethod": "POST",
    "IsController": true,
    "Order": 0,
    "Parameters": [
      {
        "Name": "model",
        "Type": "APIBanXeDap.ViewModels.Login",
        "IsRequired": true
      }
    ],
    "ReturnTypes": []
  },
  {
    "ContainingType": "APIBanXeDap.Controllers.AccountsController",
    "Method": "LoginGoogle",
    "RelativePath": "api/Accounts/LoginGoogle",
    "HttpMethod": "GET",
    "IsController": true,
    "Order": 0,
    "Parameters": [],
    "ReturnTypes": [
      {
        "Type": "System.Void",
        "MediaTypes": [],
        "StatusCode": 200
      }
    ]
  },
  {
    "ContainingType": "APIBanXeDap.Controllers.AccountsController",
    "Method": "LoginStaff",
    "RelativePath": "api/Accounts/LoginStaff",
    "HttpMethod": "POST",
    "IsController": true,
    "Order": 0,
    "Parameters": [
      {
        "Name": "model",
        "Type": "APIBanXeDap.ViewModels.Login",
        "IsRequired": true
      }
    ],
    "ReturnTypes": []
  },
  {
    "ContainingType": "APIBanXeDap.Controllers.AccountsController",
    "Method": "Logout",
    "RelativePath": "api/Accounts/Logout",
    "HttpMethod": "DELETE",
    "IsController": true,
    "Order": 0,
    "Parameters": [
      {
        "Name": "RefreshToken",
        "Type": "System.String",
        "IsRequired": false
      }
    ],
    "ReturnTypes": []
  },
  {
    "ContainingType": "APIBanXeDap.Controllers.AccountsController",
    "Method": "Register",
    "RelativePath": "api/Accounts/Register",
    "HttpMethod": "POST",
    "IsController": true,
    "Order": 0,
    "Parameters": [
      {
        "Name": "model",
        "Type": "APIBanXeDap.ViewModels.Register",
        "IsRequired": true
      }
    ],
    "ReturnTypes": []
  },
  {
    "ContainingType": "APIBanXeDap.Controllers.AccountsController",
    "Method": "RenewToken",
    "RelativePath": "api/Accounts/RenewAccessToken",
    "HttpMethod": "POST",
    "IsController": true,
    "Order": 0,
    "Parameters": [
      {
        "Name": "model",
        "Type": "APIBanXeDap.ViewModels.PersonalInformation",
        "IsRequired": true
      }
    ],
    "ReturnTypes": []
  },
  {
    "ContainingType": "APIBanXeDap.Controllers.BillController",
    "Method": "ChangeStatusOrder",
    "RelativePath": "api/Bill/ChangeStatusOrder",
    "HttpMethod": "PUT",
    "IsController": true,
    "Order": 0,
    "Parameters": [
      {
        "Name": "idOrder",
        "Type": "System.Int32",
        "IsRequired": false
      },
      {
        "Name": "idStaff",
        "Type": "System.Int32",
        "IsRequired": false
      },
      {
        "Name": "statusOrder",
        "Type": "System.String",
        "IsRequired": false
      }
    ],
    "ReturnTypes": []
  },
  {
    "ContainingType": "APIBanXeDap.Controllers.BillController",
    "Method": "Get",
    "RelativePath": "api/Bill/Get",
    "HttpMethod": "GET",
    "IsController": true,
    "Order": 0,
    "Parameters": [],
    "ReturnTypes": []
  },
  {
    "ContainingType": "APIBanXeDap.Controllers.BillController",
    "Method": "Get",
    "RelativePath": "api/Bill/Get/{maHoadon}",
    "HttpMethod": "GET",
    "IsController": true,
    "Order": 0,
    "Parameters": [
      {
        "Name": "maHoadon",
        "Type": "System.Int32",
        "IsRequired": true
      }
    ],
    "ReturnTypes": []
  },
  {
    "ContainingType": "APIBanXeDap.Controllers.BillController",
    "Method": "GetAllInvoiceData",
    "RelativePath": "api/Bill/GetAllInvoiceData",
    "HttpMethod": "GET",
    "IsController": true,
    "Order": 0,
    "Parameters": [],
    "ReturnTypes": []
  },
  {
    "ContainingType": "APIBanXeDap.Controllers.BillController",
    "Method": "GetInvoiceData",
    "RelativePath": "api/Bill/GetInvoiceData/{maHoaDon}",
    "HttpMethod": "GET",
    "IsController": true,
    "Order": 0,
    "Parameters": [
      {
        "Name": "maHoaDon",
        "Type": "System.Int32",
        "IsRequired": true
      }
    ],
    "ReturnTypes": []
  },
  {
    "ContainingType": "APIBanXeDap.Controllers.BrandsController",
    "Method": "CreateBrand",
    "RelativePath": "api/Brands/CreateBrand",
    "HttpMethod": "POST",
    "IsController": true,
    "Order": 0,
    "Parameters": [
      {
        "Name": "brand",
        "Type": "APIBanXeDap.EditModels.BrandEM",
        "IsRequired": true
      }
    ],
    "ReturnTypes": []
  },
  {
    "ContainingType": "APIBanXeDap.Controllers.BrandsController",
    "Method": "DeleteBrand",
    "RelativePath": "api/Brands/DeleteBrand/{id}",
    "HttpMethod": "PUT",
    "IsController": true,
    "Order": 0,
    "Parameters": [
      {
        "Name": "id",
        "Type": "System.Int32",
        "IsRequired": true
      }
    ],
    "ReturnTypes": []
  },
  {
    "ContainingType": "APIBanXeDap.Controllers.BrandsController",
    "Method": "EditBrand",
    "RelativePath": "api/Brands/EditBrand",
    "HttpMethod": "PUT",
    "IsController": true,
    "Order": 0,
    "Parameters": [
      {
        "Name": "brand",
        "Type": "APIBanXeDap.EditModels.BrandEM",
        "IsRequired": true
      }
    ],
    "ReturnTypes": []
  },
  {
    "ContainingType": "APIBanXeDap.Controllers.BrandsController",
    "Method": "GetAllBrand",
    "RelativePath": "api/Brands/GetAllBrand",
    "HttpMethod": "GET",
    "IsController": true,
    "Order": 0,
    "Parameters": [
      {
        "Name": "keywords",
        "Type": "System.String",
        "IsRequired": false
      },
      {
        "Name": "sort",
        "Type": "System.String",
        "IsRequired": false
      },
      {
        "Name": "page",
        "Type": "System.Int32",
        "IsRequired": false
      }
    ],
    "ReturnTypes": []
  },
  {
    "ContainingType": "APIBanXeDap.Controllers.BrandsController",
    "Method": "GetBrandById",
    "RelativePath": "api/Brands/GetBrandById/{id}",
    "HttpMethod": "GET",
    "IsController": true,
    "Order": 0,
    "Parameters": [
      {
        "Name": "id",
        "Type": "System.Int32",
        "IsRequired": true
      }
    ],
    "ReturnTypes": []
  },
  {
    "ContainingType": "APIBanXeDap.Controllers.CategoriesController",
    "Method": "GetAllCategory",
    "RelativePath": "api/Categories/GetAllCategory",
    "HttpMethod": "GET",
    "IsController": true,
    "Order": 0,
    "Parameters": [],
    "ReturnTypes": []
  },
  {
    "ContainingType": "APIBanXeDap.Controllers.CheckoutsController",
    "Method": "CheckoutOrders",
    "RelativePath": "api/Checkouts/CheckoutOrders",
    "HttpMethod": "POST",
    "IsController": true,
    "Order": 0,
    "Parameters": [
      {
        "Name": "model",
        "Type": "APIBanXeDap.ViewModels.ThongTinHoaDonVM",
        "IsRequired": true
      }
    ],
    "ReturnTypes": []
  },
  {
    "ContainingType": "APIBanXeDap.Controllers.ColorsController",
    "Method": "GetAllColor",
    "RelativePath": "api/Colors/GetAllColor",
    "HttpMethod": "GET",
    "IsController": true,
    "Order": 0,
    "Parameters": [],
    "ReturnTypes": []
  },
  {
    "ContainingType": "APIBanXeDap.Controllers.CommentsController",
    "Method": "GetById",
    "RelativePath": "api/Comments/{id}",
    "HttpMethod": "GET",
    "IsController": true,
    "Order": 0,
    "Parameters": [
      {
        "Name": "id",
        "Type": "System.Int32",
        "IsRequired": true
      }
    ],
    "ReturnTypes": [
      {
        "Type": "APIBanXeDap.Models.Binhluan",
        "MediaTypes": [
          "text/plain",
          "application/json",
          "text/json"
        ],
        "StatusCode": 200
      }
    ]
  },
  {
    "ContainingType": "APIBanXeDap.Controllers.CommentsController",
    "Method": "Create",
    "RelativePath": "api/Comments/create",
    "HttpMethod": "POST",
    "IsController": true,
    "Order": 0,
    "Parameters": [
      {
        "Name": "binhLuan",
        "Type": "APIBanXeDap.Models.Binhluan",
        "IsRequired": true
      }
    ],
    "ReturnTypes": []
  },
  {
    "ContainingType": "APIBanXeDap.Controllers.CommentsController",
    "Method": "Edit",
    "RelativePath": "api/Comments/edit",
    "HttpMethod": "PUT",
    "IsController": true,
    "Order": 0,
    "Parameters": [
      {
        "Name": "binhLuan",
        "Type": "APIBanXeDap.Models.Binhluan",
        "IsRequired": true
      }
    ],
    "ReturnTypes": []
  },
  {
    "ContainingType": "APIBanXeDap.Controllers.CommentsController",
    "Method": "GetAllComments",
    "RelativePath": "api/Comments/GetAllComments",
    "HttpMethod": "GET",
    "IsController": true,
    "Order": 0,
    "Parameters": [
      {
        "Name": "keywords",
        "Type": "System.String",
        "IsRequired": false
      },
      {
        "Name": "rating",
        "Type": "System.Nullable\u00601[[System.Int32, System.Private.CoreLib, Version=8.0.0.0, Culture=neutral, PublicKeyToken=7cec85d7bea7798e]]",
        "IsRequired": false
      },
      {
        "Name": "page",
        "Type": "System.Int32",
        "IsRequired": false
      },
      {
        "Name": "pageSize",
        "Type": "System.Int32",
        "IsRequired": false
      }
    ],
    "ReturnTypes": []
  },
  {
    "ContainingType": "APIBanXeDap.Controllers.CompareProductsController",
    "Method": "AddProductToCopare",
    "RelativePath": "api/CompareProducts/AddProductToCopare/{id}",
    "HttpMethod": "GET",
    "IsController": true,
    "Order": 0,
    "Parameters": [
      {
        "Name": "id",
        "Type": "System.Int32",
        "IsRequired": true
      }
    ],
    "ReturnTypes": []
  },
  {
    "ContainingType": "APIBanXeDap.Controllers.DashboardController",
    "Method": "GetAllOrderData",
    "RelativePath": "api/Dashboard/GetAllOrderData",
    "HttpMethod": "GET",
    "IsController": true,
    "Order": 0,
    "Parameters": [],
    "ReturnTypes": []
  },
  {
    "ContainingType": "APIBanXeDap.Controllers.DashboardController",
    "Method": "GetEarningData",
    "RelativePath": "api/Dashboard/GetEarningData/{timeRange}",
    "HttpMethod": "GET",
    "IsController": true,
    "Order": 0,
    "Parameters": [
      {
        "Name": "timeRange",
        "Type": "System.String",
        "IsRequired": true
      }
    ],
    "ReturnTypes": []
  },
  {
    "ContainingType": "APIBanXeDap.Controllers.DashboardController",
    "Method": "GetEmployeeOrderStats",
    "RelativePath": "api/Dashboard/GetEmployeeOrderStats",
    "HttpMethod": "GET",
    "IsController": true,
    "Order": 0,
    "Parameters": [],
    "ReturnTypes": []
  },
  {
    "ContainingType": "APIBanXeDap.Controllers.DashboardController",
    "Method": "GetOrderOverViewData",
    "RelativePath": "api/Dashboard/GetOrderOverViewData/{timeRange}",
    "HttpMethod": "GET",
    "IsController": true,
    "Order": 0,
    "Parameters": [
      {
        "Name": "timeRange",
        "Type": "System.String",
        "IsRequired": true
      }
    ],
    "ReturnTypes": []
  },
  {
    "ContainingType": "APIBanXeDap.Controllers.DashboardController",
    "Method": "GetOrderStatusData",
    "RelativePath": "api/Dashboard/GetOrderStatusData/{timeRange}",
    "HttpMethod": "GET",
    "IsController": true,
    "Order": 0,
    "Parameters": [
      {
        "Name": "timeRange",
        "Type": "System.String",
        "IsRequired": true
      }
    ],
    "ReturnTypes": []
  },
  {
    "ContainingType": "APIBanXeDap.Controllers.DashboardController",
    "Method": "GetStatUserAsync",
    "RelativePath": "api/Dashboard/GetStatUser",
    "HttpMethod": "GET",
    "IsController": true,
    "Order": 0,
    "Parameters": [],
    "ReturnTypes": []
  },
  {
    "ContainingType": "APIBanXeDap.Controllers.DashboardController",
    "Method": "GetTopSellingProducts",
    "RelativePath": "api/Dashboard/GetTopSellingProducts",
    "HttpMethod": "GET",
    "IsController": true,
    "Order": 0,
    "Parameters": [],
    "ReturnTypes": []
  },
  {
    "ContainingType": "APIBanXeDap.Controllers.GeminiController",
    "Method": "GetResponseAsync",
    "RelativePath": "api/Gemini",
    "HttpMethod": "POST",
    "IsController": true,
    "Order": 0,
    "Parameters": [
      {
        "Name": "userInput",
        "Type": "System.String",
        "IsRequired": true
      }
    ],
    "ReturnTypes": []
  },
  {
    "ContainingType": "APIBanXeDap.Controllers.HomeController",
    "Method": "GetAllProduct",
    "RelativePath": "api/Home/GetAllProduct",
    "HttpMethod": "GET",
    "IsController": true,
    "Order": 0,
    "Parameters": [
      {
        "Name": "keywords",
        "Type": "System.String",
        "IsRequired": false
      },
      {
        "Name": "MaDanhMuc",
        "Type": "System.Nullable\u00601[[System.Int32, System.Private.CoreLib, Version=8.0.0.0, Culture=neutral, PublicKeyToken=7cec85d7bea7798e]]",
        "IsRequired": false
      },
      {
        "Name": "MaThuongHieu",
        "Type": "System.Nullable\u00601[[System.Int32, System.Private.CoreLib, Version=8.0.0.0, Culture=neutral, PublicKeyToken=7cec85d7bea7798e]]",
        "IsRequired": false
      },
      {
        "Name": "sort",
        "Type": "System.String",
        "IsRequired": false
      },
      {
        "Name": "page",
        "Type": "System.Int32",
        "IsRequired": false
      }
    ],
    "ReturnTypes": []
  },
  {
    "ContainingType": "APIBanXeDap.Controllers.HomeController",
    "Method": "GetProductById",
    "RelativePath": "api/Home/GetProductById/{id}",
    "HttpMethod": "GET",
    "IsController": true,
    "Order": 0,
    "Parameters": [
      {
        "Name": "id",
        "Type": "System.Int32",
        "IsRequired": true
      }
    ],
    "ReturnTypes": []
  },
  {
    "ContainingType": "APIBanXeDap.Controllers.HomeController",
    "Method": "GetSanPhamLienQuan",
    "RelativePath": "api/Home/GetSanPhamLienQuan/{dm}",
    "HttpMethod": "GET",
    "IsController": true,
    "Order": 0,
    "Parameters": [
      {
        "Name": "dm",
        "Type": "System.String",
        "IsRequired": true
      }
    ],
    "ReturnTypes": []
  },
  {
    "ContainingType": "APIBanXeDap.Controllers.HomeController",
    "Method": "GetSanPhamBanChay",
    "RelativePath": "api/Home/SanPhamBanChay",
    "HttpMethod": "GET",
    "IsController": true,
    "Order": 0,
    "Parameters": [],
    "ReturnTypes": []
  },
  {
    "ContainingType": "APIBanXeDap.Controllers.KhachHangController",
    "Method": "Add",
    "RelativePath": "api/KhachHang/Add",
    "HttpMethod": "POST",
    "IsController": true,
    "Order": 0,
    "Parameters": [
      {
        "Name": "MaKh",
        "Type": "System.Int32",
        "IsRequired": false
      },
      {
        "Name": "HoTen",
        "Type": "System.String",
        "IsRequired": false
      },
      {
        "Name": "Cccd",
        "Type": "System.String",
        "IsRequired": false
      },
      {
        "Name": "Sdt",
        "Type": "System.String",
        "IsRequired": false
      },
      {
        "Name": "Email",
        "Type": "System.String",
        "IsRequired": false
      },
      {
        "Name": "TenTaiKhoan",
        "Type": "System.String",
        "IsRequired": false
      },
      {
        "Name": "MatKhau",
        "Type": "System.String",
        "IsRequired": false
      },
      {
        "Name": "GioiTinh",
        "Type": "System.String",
        "IsRequired": false
      },
      {
        "Name": "NgaySinh",
        "Type": "System.Nullable\u00601[[System.DateOnly, System.Private.CoreLib, Version=8.0.0.0, Culture=neutral, PublicKeyToken=7cec85d7bea7798e]]",
        "IsRequired": false
      },
      {
        "Name": "DiaChi",
        "Type": "System.String",
        "IsRequired": false
      },
      {
        "Name": "TinhTrang",
        "Type": "System.String",
        "IsRequired": false
      },
      {
        "Name": "Hinh",
        "Type": "System.String",
        "IsRequired": false
      },
      {
        "Name": "Anh",
        "Type": "Microsoft.AspNetCore.Http.IFormFile",
        "IsRequired": false
      },
      {
        "Name": "IsDelete",
        "Type": "System.Nullable\u00601[[System.Boolean, System.Private.CoreLib, Version=8.0.0.0, Culture=neutral, PublicKeyToken=7cec85d7bea7798e]]",
        "IsRequired": false
      }
    ],
    "ReturnTypes": []
  },
  {
    "ContainingType": "APIBanXeDap.Controllers.KhachHangController",
    "Method": "GetAll",
    "RelativePath": "api/KhachHang/GetAll",
    "HttpMethod": "GET",
    "IsController": true,
    "Order": 0,
    "Parameters": [
      {
        "Name": "keyword",
        "Type": "System.String",
        "IsRequired": false
      },
      {
        "Name": "sort",
        "Type": "System.String",
        "IsRequired": false
      }
    ],
    "ReturnTypes": []
  },
  {
    "ContainingType": "APIBanXeDap.Controllers.KhachHangController",
    "Method": "GetKhachHangById",
    "RelativePath": "api/KhachHang/GetKhachHangById/{id}",
    "HttpMethod": "GET",
    "IsController": true,
    "Order": 0,
    "Parameters": [
      {
        "Name": "id",
        "Type": "System.Int32",
        "IsRequired": true
      }
    ],
    "ReturnTypes": []
  },
  {
    "ContainingType": "APIBanXeDap.Controllers.KhachHangController",
    "Method": "GetPaged",
    "RelativePath": "api/KhachHang/GetPaged",
    "HttpMethod": "GET",
    "IsController": true,
    "Order": 0,
    "Parameters": [
      {
        "Name": "pageNumber",
        "Type": "System.Int32",
        "IsRequired": false
      },
      {
        "Name": "pageSize",
        "Type": "System.Int32",
        "IsRequired": false
      },
      {
        "Name": "keyword",
        "Type": "System.String",
        "IsRequired": false
      },
      {
        "Name": "sort",
        "Type": "System.String",
        "IsRequired": false
      },
      {
        "Name": "status",
        "Type": "System.String",
        "IsRequired": false
      },
      {
        "Name": "gender",
        "Type": "System.String",
        "IsRequired": false
      }
    ],
    "ReturnTypes": []
  },
  {
    "ContainingType": "APIBanXeDap.Controllers.KhachHangController",
    "Method": "ImportExcel",
    "RelativePath": "api/KhachHang/ImportExcel",
    "HttpMethod": "POST",
    "IsController": true,
    "Order": 0,
    "Parameters": [
      {
        "Name": "file",
        "Type": "Microsoft.AspNetCore.Http.IFormFile",
        "IsRequired": false
      }
    ],
    "ReturnTypes": []
  },
  {
    "ContainingType": "APIBanXeDap.Controllers.KhachHangController",
    "Method": "Search",
    "RelativePath": "api/KhachHang/Search",
    "HttpMethod": "GET",
    "IsController": true,
    "Order": 0,
    "Parameters": [
      {
        "Name": "keyword",
        "Type": "System.String",
        "IsRequired": false
      },
      {
        "Name": "sort",
        "Type": "System.String",
        "IsRequired": false
      }
    ],
    "ReturnTypes": []
  },
  {
    "ContainingType": "APIBanXeDap.Controllers.KhachHangController",
    "Method": "ToggleIsDelete",
    "RelativePath": "api/KhachHang/ToggleIsDelete/{id}",
    "HttpMethod": "PUT",
    "IsController": true,
    "Order": 0,
    "Parameters": [
      {
        "Name": "id",
        "Type": "System.Int32",
        "IsRequired": true
      }
    ],
    "ReturnTypes": []
  },
  {
    "ContainingType": "APIBanXeDap.Controllers.KhachHangController",
    "Method": "ToggleStatus",
    "RelativePath": "api/KhachHang/ToggleStatus/{id}",
    "HttpMethod": "POST",
    "IsController": true,
    "Order": 0,
    "Parameters": [
      {
        "Name": "id",
        "Type": "System.Int32",
        "IsRequired": true
      },
      {
        "Name": "status",
        "Type": "System.String",
        "IsRequired": true
      }
    ],
    "ReturnTypes": []
  },
  {
    "ContainingType": "APIBanXeDap.Controllers.KhachHangController",
    "Method": "Update",
    "RelativePath": "api/KhachHang/Update/{id}",
    "HttpMethod": "PUT",
    "IsController": true,
    "Order": 0,
    "Parameters": [
      {
        "Name": "id",
        "Type": "System.Int32",
        "IsRequired": true
      },
      {
        "Name": "MaKh",
        "Type": "System.Int32",
        "IsRequired": false
      },
      {
        "Name": "HoTen",
        "Type": "System.String",
        "IsRequired": false
      },
      {
        "Name": "Cccd",
        "Type": "System.String",
        "IsRequired": false
      },
      {
        "Name": "Sdt",
        "Type": "System.String",
        "IsRequired": false
      },
      {
        "Name": "Email",
        "Type": "System.String",
        "IsRequired": false
      },
      {
        "Name": "TenTaiKhoan",
        "Type": "System.String",
        "IsRequired": false
      },
      {
        "Name": "MatKhau",
        "Type": "System.String",
        "IsRequired": false
      },
      {
        "Name": "GioiTinh",
        "Type": "System.String",
        "IsRequired": false
      },
      {
        "Name": "NgaySinh",
        "Type": "System.Nullable\u00601[[System.DateOnly, System.Private.CoreLib, Version=8.0.0.0, Culture=neutral, PublicKeyToken=7cec85d7bea7798e]]",
        "IsRequired": false
      },
      {
        "Name": "DiaChi",
        "Type": "System.String",
        "IsRequired": false
      },
      {
        "Name": "TinhTrang",
        "Type": "System.String",
        "IsRequired": false
      },
      {
        "Name": "Hinh",
        "Type": "System.String",
        "IsRequired": false
      },
      {
        "Name": "Anh",
        "Type": "Microsoft.AspNetCore.Http.IFormFile",
        "IsRequired": false
      },
      {
        "Name": "IsDelete",
        "Type": "System.Nullable\u00601[[System.Boolean, System.Private.CoreLib, Version=8.0.0.0, Culture=neutral, PublicKeyToken=7cec85d7bea7798e]]",
        "IsRequired": false
      }
    ],
    "ReturnTypes": []
  },
  {
    "ContainingType": "APIBanXeDap.Controllers.MaCouponsController",
    "Method": "Cancel",
    "RelativePath": "api/MaCoupons/Cancel",
    "HttpMethod": "PUT",
    "IsController": true,
    "Order": 0,
    "Parameters": [
      {
        "Name": "id",
        "Type": "System.String",
        "IsRequired": false
      }
    ],
    "ReturnTypes": []
  },
  {
    "ContainingType": "APIBanXeDap.Controllers.MaCouponsController",
    "Method": "Create",
    "RelativePath": "api/MaCoupons/Create",
    "HttpMethod": "POST",
    "IsController": true,
    "Order": 0,
    "Parameters": [
      {
        "Name": "model",
        "Type": "APIBanXeDap.ViewModels.MaCouponVM",
        "IsRequired": true
      }
    ],
    "ReturnTypes": []
  },
  {
    "ContainingType": "APIBanXeDap.Controllers.MaCouponsController",
    "Method": "GetAll",
    "RelativePath": "api/MaCoupons/GetAll",
    "HttpMethod": "GET",
    "IsController": true,
    "Order": 0,
    "Parameters": [],
    "ReturnTypes": []
  },
  {
    "ContainingType": "APIBanXeDap.Controllers.MaCouponsController",
    "Method": "GetAllByPage",
    "RelativePath": "api/MaCoupons/GetAllCouponCodeByPage",
    "HttpMethod": "GET",
    "IsController": true,
    "Order": 0,
    "Parameters": [
      {
        "Name": "keywords",
        "Type": "System.String",
        "IsRequired": false
      },
      {
        "Name": "status",
        "Type": "System.String",
        "IsRequired": false
      },
      {
        "Name": "sort",
        "Type": "System.String",
        "IsRequired": false
      },
      {
        "Name": "page",
        "Type": "System.Int32",
        "IsRequired": false
      }
    ],
    "ReturnTypes": []
  },
  {
    "ContainingType": "APIBanXeDap.Controllers.MaCouponsController",
    "Method": "Update",
    "RelativePath": "api/MaCoupons/Update",
    "HttpMethod": "PUT",
    "IsController": true,
    "Order": 0,
    "Parameters": [
      {
        "Name": "model",
        "Type": "APIBanXeDap.ViewModels.MaCouponVM",
        "IsRequired": true
      }
    ],
    "ReturnTypes": []
  },
  {
    "ContainingType": "APIBanXeDap.Controllers.NhanVienController",
    "Method": "Add",
    "RelativePath": "api/NhanVien/Add",
    "HttpMethod": "POST",
    "IsController": true,
    "Order": 0,
    "Parameters": [
      {
        "Name": "MaNv",
        "Type": "System.Int32",
        "IsRequired": false
      },
      {
        "Name": "HoTen",
        "Type": "System.String",
        "IsRequired": false
      },
      {
        "Name": "GioiTinh",
        "Type": "System.String",
        "IsRequired": false
      },
      {
        "Name": "NgaySinh",
        "Type": "System.Nullable\u00601[[System.DateOnly, System.Private.CoreLib, Version=8.0.0.0, Culture=neutral, PublicKeyToken=7cec85d7bea7798e]]",
        "IsRequired": false
      },
      {
        "Name": "DiaChi",
        "Type": "System.String",
        "IsRequired": false
      },
      {
        "Name": "Cccd",
        "Type": "System.String",
        "IsRequired": false
      },
      {
        "Name": "Sdt",
        "Type": "System.String",
        "IsRequired": false
      },
      {
        "Name": "Email",
        "Type": "System.String",
        "IsRequired": false
      },
      {
        "Name": "NgayVaoLam",
        "Type": "System.DateOnly",
        "IsRequired": false
      },
      {
        "Name": "Luong",
        "Type": "System.Int32",
        "IsRequired": false
      },
      {
        "Name": "VaiTro",
        "Type": "System.String",
        "IsRequired": false
      },
      {
        "Name": "TenTaiKhoan",
        "Type": "System.String",
        "IsRequired": false
      },
      {
        "Name": "MatKhau",
        "Type": "System.String",
        "IsRequired": false
      },
      {
        "Name": "TinhTrang",
        "Type": "System.String",
        "IsRequired": false
      },
      {
        "Name": "IsDelete",
        "Type": "System.Nullable\u00601[[System.Boolean, System.Private.CoreLib, Version=8.0.0.0, Culture=neutral, PublicKeyToken=7cec85d7bea7798e]]",
        "IsRequired": false
      },
      {
        "Name": "Hinh",
        "Type": "System.String",
        "IsRequired": false
      },
      {
        "Name": "Anh",
        "Type": "Microsoft.AspNetCore.Http.IFormFile",
        "IsRequired": false
      },
      {
        "Name": "SoDonHangXuLy",
        "Type": "System.Int32",
        "IsRequired": false
      },
      {
        "Name": "DoanhThuMangLai",
        "Type": "System.Int32",
        "IsRequired": false
      }
    ],
    "ReturnTypes": []
  },
  {
    "ContainingType": "APIBanXeDap.Controllers.NhanVienController",
    "Method": "ExportExcel",
    "RelativePath": "api/NhanVien/ExportExcel",
    "HttpMethod": "GET",
    "IsController": true,
    "Order": 0,
    "Parameters": [
      {
        "Name": "keyword",
        "Type": "System.String",
        "IsRequired": false
      },
      {
        "Name": "sort",
        "Type": "System.String",
        "IsRequired": false
      },
      {
        "Name": "status",
        "Type": "System.String",
        "IsRequired": false
      },
      {
        "Name": "gender",
        "Type": "System.String",
        "IsRequired": false
      }
    ],
    "ReturnTypes": []
  },
  {
    "ContainingType": "APIBanXeDap.Controllers.NhanVienController",
    "Method": "GetAll",
    "RelativePath": "api/NhanVien/GetAll",
    "HttpMethod": "GET",
    "IsController": true,
    "Order": 0,
    "Parameters": [
      {
        "Name": "keyword",
        "Type": "System.String",
        "IsRequired": false
      },
      {
        "Name": "sort",
        "Type": "System.String",
        "IsRequired": false
      },
      {
        "Name": "status",
        "Type": "System.String",
        "IsRequired": false
      },
      {
        "Name": "gender",
        "Type": "System.String",
        "IsRequired": false
      }
    ],
    "ReturnTypes": []
  },
  {
    "ContainingType": "APIBanXeDap.Controllers.NhanVienController",
    "Method": "GetNhanVienById",
    "RelativePath": "api/NhanVien/GetNhanVienById/{id}",
    "HttpMethod": "GET",
    "IsController": true,
    "Order": 0,
    "Parameters": [
      {
        "Name": "id",
        "Type": "System.Int32",
        "IsRequired": true
      }
    ],
    "ReturnTypes": []
  },
  {
    "ContainingType": "APIBanXeDap.Controllers.NhanVienController",
    "Method": "GetPaged",
    "RelativePath": "api/NhanVien/GetPaged",
    "HttpMethod": "GET",
    "IsController": true,
    "Order": 0,
    "Parameters": [
      {
        "Name": "pageNumber",
        "Type": "System.Int32",
        "IsRequired": false
      },
      {
        "Name": "pageSize",
        "Type": "System.Int32",
        "IsRequired": false
      },
      {
        "Name": "keyword",
        "Type": "System.String",
        "IsRequired": false
      },
      {
        "Name": "sort",
        "Type": "System.String",
        "IsRequired": false
      },
      {
        "Name": "status",
        "Type": "System.String",
        "IsRequired": false
      },
      {
        "Name": "gender",
        "Type": "System.String",
        "IsRequired": false
      }
    ],
    "ReturnTypes": []
  },
  {
    "ContainingType": "APIBanXeDap.Controllers.NhanVienController",
    "Method": "ImportExcel",
    "RelativePath": "api/NhanVien/ImportExcel",
    "HttpMethod": "POST",
    "IsController": true,
    "Order": 0,
    "Parameters": [
      {
        "Name": "file",
        "Type": "Microsoft.AspNetCore.Http.IFormFile",
        "IsRequired": false
      }
    ],
    "ReturnTypes": []
  },
  {
    "ContainingType": "APIBanXeDap.Controllers.NhanVienController",
    "Method": "Search",
    "RelativePath": "api/NhanVien/Search",
    "HttpMethod": "GET",
    "IsController": true,
    "Order": 0,
    "Parameters": [
      {
        "Name": "keyword",
        "Type": "System.String",
        "IsRequired": false
      },
      {
        "Name": "sort",
        "Type": "System.String",
        "IsRequired": false
      },
      {
        "Name": "status",
        "Type": "System.String",
        "IsRequired": false
      },
      {
        "Name": "gender",
        "Type": "System.String",
        "IsRequired": false
      }
    ],
    "ReturnTypes": []
  },
  {
    "ContainingType": "APIBanXeDap.Controllers.NhanVienController",
    "Method": "ToggleIsDelete",
    "RelativePath": "api/NhanVien/ToggleIsDelete/{id}",
    "HttpMethod": "PUT",
    "IsController": true,
    "Order": 0,
    "Parameters": [
      {
        "Name": "id",
        "Type": "System.Int32",
        "IsRequired": true
      }
    ],
    "ReturnTypes": []
  },
  {
    "ContainingType": "APIBanXeDap.Controllers.NhanVienController",
    "Method": "ToggleStatus",
    "RelativePath": "api/NhanVien/ToggleStatus/{id}",
    "HttpMethod": "POST",
    "IsController": true,
    "Order": 0,
    "Parameters": [
      {
        "Name": "id",
        "Type": "System.Int32",
        "IsRequired": true
      },
      {
        "Name": "status",
        "Type": "System.String",
        "IsRequired": true
      }
    ],
    "ReturnTypes": []
  },
  {
    "ContainingType": "APIBanXeDap.Controllers.NhanVienController",
    "Method": "Update",
    "RelativePath": "api/NhanVien/Update/{id}",
    "HttpMethod": "PUT",
    "IsController": true,
    "Order": 0,
    "Parameters": [
      {
        "Name": "id",
        "Type": "System.Int32",
        "IsRequired": true
      },
      {
        "Name": "MaNv",
        "Type": "System.Int32",
        "IsRequired": false
      },
      {
        "Name": "HoTen",
        "Type": "System.String",
        "IsRequired": false
      },
      {
        "Name": "GioiTinh",
        "Type": "System.String",
        "IsRequired": false
      },
      {
        "Name": "NgaySinh",
        "Type": "System.Nullable\u00601[[System.DateOnly, System.Private.CoreLib, Version=8.0.0.0, Culture=neutral, PublicKeyToken=7cec85d7bea7798e]]",
        "IsRequired": false
      },
      {
        "Name": "DiaChi",
        "Type": "System.String",
        "IsRequired": false
      },
      {
        "Name": "Cccd",
        "Type": "System.String",
        "IsRequired": false
      },
      {
        "Name": "Sdt",
        "Type": "System.String",
        "IsRequired": false
      },
      {
        "Name": "Email",
        "Type": "System.String",
        "IsRequired": false
      },
      {
        "Name": "NgayVaoLam",
        "Type": "System.DateOnly",
        "IsRequired": false
      },
      {
        "Name": "Luong",
        "Type": "System.Int32",
        "IsRequired": false
      },
      {
        "Name": "VaiTro",
        "Type": "System.String",
        "IsRequired": false
      },
      {
        "Name": "TenTaiKhoan",
        "Type": "System.String",
        "IsRequired": false
      },
      {
        "Name": "MatKhau",
        "Type": "System.String",
        "IsRequired": false
      },
      {
        "Name": "TinhTrang",
        "Type": "System.String",
        "IsRequired": false
      },
      {
        "Name": "IsDelete",
        "Type": "System.Nullable\u00601[[System.Boolean, System.Private.CoreLib, Version=8.0.0.0, Culture=neutral, PublicKeyToken=7cec85d7bea7798e]]",
        "IsRequired": false
      },
      {
        "Name": "Hinh",
        "Type": "System.String",
        "IsRequired": false
      },
      {
        "Name": "Anh",
        "Type": "Microsoft.AspNetCore.Http.IFormFile",
        "IsRequired": false
      },
      {
        "Name": "SoDonHangXuLy",
        "Type": "System.Int32",
        "IsRequired": false
      },
      {
        "Name": "DoanhThuMangLai",
        "Type": "System.Int32",
        "IsRequired": false
      }
    ],
    "ReturnTypes": []
  },
  {
    "ContainingType": "APIBanXeDap.Controllers.ProductDetailsController",
    "Method": "CreateAllProductDetails",
    "RelativePath": "api/ProductDetails/CreateAllProductDetails",
    "HttpMethod": "POST",
    "IsController": true,
    "Order": 0,
    "Parameters": [
      {
        "Name": "model",
        "Type": "APIBanXeDap.EditModels.DetailsProductEM",
        "IsRequired": true
      }
    ],
    "ReturnTypes": []
  },
  {
    "ContainingType": "APIBanXeDap.Controllers.ProductDetailsController",
    "Method": "DeleteDetailsProduct",
    "RelativePath": "api/ProductDetails/DeleteDetailsProduct",
    "HttpMethod": "DELETE",
    "IsController": true,
    "Order": 0,
    "Parameters": [
      {
        "Name": "MaSP",
        "Type": "System.Int32",
        "IsRequired": false
      },
      {
        "Name": "MaMau",
        "Type": "System.Int32",
        "IsRequired": false
      },
      {
        "Name": "MaKichThuoc",
        "Type": "System.Int32",
        "IsRequired": false
      }
    ],
    "ReturnTypes": []
  },
  {
    "ContainingType": "APIBanXeDap.Controllers.ProductDetailsController",
    "Method": "EditDetailsProduct",
    "RelativePath": "api/ProductDetails/EditDetailsProduct",
    "HttpMethod": "PUT",
    "IsController": true,
    "Order": 0,
    "Parameters": [
      {
        "Name": "model",
        "Type": "APIBanXeDap.EditModels.DetailsProductEM",
        "IsRequired": true
      }
    ],
    "ReturnTypes": []
  },
  {
    "ContainingType": "APIBanXeDap.Controllers.ProductDetailsController",
    "Method": "GetAllProductDetails",
    "RelativePath": "api/ProductDetails/GetAllProductDetails",
    "HttpMethod": "GET",
    "IsController": true,
    "Order": 0,
    "Parameters": [],
    "ReturnTypes": []
  },
  {
    "ContainingType": "APIBanXeDap.Controllers.ProductImagesController",
    "Method": "CreateProductImage",
    "RelativePath": "api/ProductImages/CreateProductImage",
    "HttpMethod": "POST",
    "IsController": true,
    "Order": 0,
    "Parameters": [
      {
        "Name": "model",
        "Type": "APIBanXeDap.EditModels.ProductImgEM",
        "IsRequired": true
      }
    ],
    "ReturnTypes": []
  },
  {
    "ContainingType": "APIBanXeDap.Controllers.ProductImagesController",
    "Method": "DeleteProductImage",
    "RelativePath": "api/ProductImages/DeleteProductImage/{id}",
    "HttpMethod": "DELETE",
    "IsController": true,
    "Order": 0,
    "Parameters": [
      {
        "Name": "id",
        "Type": "System.Int32",
        "IsRequired": true
      }
    ],
    "ReturnTypes": []
  },
  {
    "ContainingType": "APIBanXeDap.Controllers.ProductImagesController",
    "Method": "GetAllProductImages",
    "RelativePath": "api/ProductImages/GetAllProductImages",
    "HttpMethod": "GET",
    "IsController": true,
    "Order": 0,
    "Parameters": [],
    "ReturnTypes": []
  },
  {
    "ContainingType": "APIBanXeDap.Controllers.ProductsController",
    "Method": "CreateProduct",
    "RelativePath": "api/Products/CreateProduct",
    "HttpMethod": "POST",
    "IsController": true,
    "Order": 0,
    "Parameters": [
      {
        "Name": "product",
        "Type": "APIBanXeDap.EditModels.ProductEM",
        "IsRequired": true
      }
    ],
    "ReturnTypes": []
  },
  {
    "ContainingType": "APIBanXeDap.Controllers.ProductsController",
    "Method": "DeleteProduct",
    "RelativePath": "api/Products/DeleteProduct/{id}",
    "HttpMethod": "PUT",
    "IsController": true,
    "Order": 0,
    "Parameters": [
      {
        "Name": "id",
        "Type": "System.Int32",
        "IsRequired": true
      }
    ],
    "ReturnTypes": []
  },
  {
    "ContainingType": "APIBanXeDap.Controllers.ProductsController",
    "Method": "EditProduct",
    "RelativePath": "api/Products/EditProduct",
    "HttpMethod": "PUT",
    "IsController": true,
    "Order": 0,
    "Parameters": [
      {
        "Name": "product",
        "Type": "APIBanXeDap.EditModels.ProductEM",
        "IsRequired": true
      }
    ],
    "ReturnTypes": []
  },
  {
    "ContainingType": "APIBanXeDap.Controllers.ProductsController",
    "Method": "GetAllProduct",
    "RelativePath": "api/Products/GetAllProduct",
    "HttpMethod": "GET",
    "IsController": true,
    "Order": 0,
    "Parameters": [
      {
        "Name": "keywords",
        "Type": "System.String",
        "IsRequired": false
      },
      {
        "Name": "MaDanhMuc",
        "Type": "System.Nullable\u00601[[System.Int32, System.Private.CoreLib, Version=8.0.0.0, Culture=neutral, PublicKeyToken=7cec85d7bea7798e]]",
        "IsRequired": false
      },
      {
        "Name": "MaThuongHieu",
        "Type": "System.Nullable\u00601[[System.Int32, System.Private.CoreLib, Version=8.0.0.0, Culture=neutral, PublicKeyToken=7cec85d7bea7798e]]",
        "IsRequired": false
      },
      {
        "Name": "sort",
        "Type": "System.String",
        "IsRequired": false
      },
      {
        "Name": "page",
        "Type": "System.Int32",
        "IsRequired": false
      }
    ],
    "ReturnTypes": []
  },
  {
    "ContainingType": "APIBanXeDap.Controllers.ProductsController",
    "Method": "GetProductById",
    "RelativePath": "api/Products/GetProductById/{id}",
    "HttpMethod": "GET",
    "IsController": true,
    "Order": 0,
    "Parameters": [
      {
        "Name": "id",
        "Type": "System.Int32",
        "IsRequired": true
      }
    ],
    "ReturnTypes": []
  },
  {
    "ContainingType": "APIBanXeDap.Controllers.ReplysController",
    "Method": "GetAllReplies",
    "RelativePath": "api/Replys",
    "HttpMethod": "GET",
    "IsController": true,
    "Order": 0,
    "Parameters": [],
    "ReturnTypes": []
  },
  {
    "ContainingType": "APIBanXeDap.Controllers.ReplysController",
    "Method": "CreateReply",
    "RelativePath": "api/Replys",
    "HttpMethod": "POST",
    "IsController": true,
    "Order": 0,
    "Parameters": [
      {
        "Name": "reply",
        "Type": "APIBanXeDap.Models.Traloibinhluan",
        "IsRequired": true
      }
    ],
    "ReturnTypes": []
  },
  {
    "ContainingType": "APIBanXeDap.Controllers.ReplysController",
    "Method": "GetReplyById",
    "RelativePath": "api/Replys/{id}",
    "HttpMethod": "GET",
    "IsController": true,
    "Order": 0,
    "Parameters": [
      {
        "Name": "id",
        "Type": "System.Int32",
        "IsRequired": true
      }
    ],
    "ReturnTypes": []
  },
  {
    "ContainingType": "APIBanXeDap.Controllers.ReplysController",
    "Method": "UpdateReply",
    "RelativePath": "api/Replys/{id}",
    "HttpMethod": "PUT",
    "IsController": true,
    "Order": 0,
    "Parameters": [
      {
        "Name": "id",
        "Type": "System.Int32",
        "IsRequired": true
      },
      {
        "Name": "reply",
        "Type": "APIBanXeDap.Models.Traloibinhluan",
        "IsRequired": true
      }
    ],
    "ReturnTypes": []
  },
  {
    "ContainingType": "APIBanXeDap.Controllers.ReplysController",
    "Method": "DeleteReply",
    "RelativePath": "api/Replys/{id}",
    "HttpMethod": "DELETE",
    "IsController": true,
    "Order": 0,
    "Parameters": [
      {
        "Name": "id",
        "Type": "System.Int32",
        "IsRequired": true
      }
    ],
    "ReturnTypes": []
  },
  {
    "ContainingType": "APIBanXeDap.Controllers.ShippingsController",
    "Method": "Create",
    "RelativePath": "api/Shippings/CreateShipping",
    "HttpMethod": "POST",
    "IsController": true,
    "Order": 0,
    "Parameters": [
      {
        "Name": "model",
        "Type": "APIBanXeDap.ViewModels.ShippingVM",
        "IsRequired": true
      }
    ],
    "ReturnTypes": []
  },
  {
    "ContainingType": "APIBanXeDap.Controllers.ShippingsController",
    "Method": "Delete",
    "RelativePath": "api/Shippings/DeleteShipping/{id}",
    "HttpMethod": "DELETE",
    "IsController": true,
    "Order": 0,
    "Parameters": [
      {
        "Name": "id",
        "Type": "System.Int32",
        "IsRequired": true
      }
    ],
    "ReturnTypes": []
  },
  {
    "ContainingType": "APIBanXeDap.Controllers.ShippingsController",
    "Method": "Edit",
    "RelativePath": "api/Shippings/EditShipping",
    "HttpMethod": "PUT",
    "IsController": true,
    "Order": 0,
    "Parameters": [
      {
        "Name": "model",
        "Type": "APIBanXeDap.ViewModels.ShippingVM",
        "IsRequired": true
      }
    ],
    "ReturnTypes": []
  },
  {
    "ContainingType": "APIBanXeDap.Controllers.ShippingsController",
    "Method": "Get",
    "RelativePath": "api/Shippings/GetAll",
    "HttpMethod": "GET",
    "IsController": true,
    "Order": 0,
    "Parameters": [
      {
        "Name": "keywords",
        "Type": "System.String",
        "IsRequired": false
      },
      {
        "Name": "priceFilter",
        "Type": "System.String",
        "IsRequired": false
      },
      {
        "Name": "SortByPrice",
        "Type": "System.String",
        "IsRequired": false
      },
      {
        "Name": "page",
        "Type": "System.Int32",
        "IsRequired": false
      }
    ],
    "ReturnTypes": []
  },
  {
    "ContainingType": "APIBanXeDap.Controllers.ShippingsController",
    "Method": "GetShippingFee",
    "RelativePath": "api/Shippings/GetShippingFee",
    "HttpMethod": "GET",
    "IsController": true,
    "Order": 0,
    "Parameters": [
      {
        "Name": "pho",
        "Type": "System.String",
        "IsRequired": false
      },
      {
        "Name": "quan",
        "Type": "System.String",
        "IsRequired": false
      },
      {
        "Name": "phuong",
        "Type": "System.String",
        "IsRequired": false
      }
    ],
    "ReturnTypes": []
  },
  {
    "ContainingType": "APIBanXeDap.Controllers.SizesController",
    "Method": "GetAllSize",
    "RelativePath": "api/Sizes/GetAllSize",
    "HttpMethod": "GET",
    "IsController": true,
    "Order": 0,
    "Parameters": [],
    "ReturnTypes": []
  },
  {
    "ContainingType": "APIBanXeDap.Controllers.SuppliersController",
    "Method": "GetSupplierById",
    "RelativePath": "api/Suppliers/{id}",
    "HttpMethod": "GET",
    "IsController": true,
    "Order": 0,
    "Parameters": [
      {
        "Name": "id",
        "Type": "System.Int32",
        "IsRequired": true
      }
    ],
    "ReturnTypes": []
  },
  {
    "ContainingType": "APIBanXeDap.Controllers.SuppliersController",
    "Method": "CreateSupplier",
    "RelativePath": "api/Suppliers/CreateSupplier",
    "HttpMethod": "POST",
    "IsController": true,
    "Order": 0,
    "Parameters": [
      {
        "Name": "supplier",
        "Type": "APIBanXeDap.EditModels.SupplierEM",
        "IsRequired": true
      }
    ],
    "ReturnTypes": []
  },
  {
    "ContainingType": "APIBanXeDap.Controllers.SuppliersController",
    "Method": "DeleteSupplier",
    "RelativePath": "api/Suppliers/DeleteSupplier/{id}",
    "HttpMethod": "PUT",
    "IsController": true,
    "Order": 0,
    "Parameters": [
      {
        "Name": "id",
        "Type": "System.Int32",
        "IsRequired": true
      }
    ],
    "ReturnTypes": []
  },
  {
    "ContainingType": "APIBanXeDap.Controllers.SuppliersController",
    "Method": "EditSupplier",
    "RelativePath": "api/Suppliers/EditSupplier",
    "HttpMethod": "PUT",
    "IsController": true,
    "Order": 0,
    "Parameters": [
      {
        "Name": "supplier",
        "Type": "APIBanXeDap.EditModels.SupplierEM",
        "IsRequired": true
      }
    ],
    "ReturnTypes": []
  },
  {
    "ContainingType": "APIBanXeDap.Controllers.SuppliersController",
    "Method": "GetAllSupplier",
    "RelativePath": "api/Suppliers/GetAllSupplier",
    "HttpMethod": "GET",
    "IsController": true,
    "Order": 0,
    "Parameters": [
      {
        "Name": "keywords",
        "Type": "System.String",
        "IsRequired": false
      },
      {
        "Name": "sort",
        "Type": "System.String",
        "IsRequired": false
      },
      {
        "Name": "page",
        "Type": "System.Int32",
        "IsRequired": false
      }
    ],
    "ReturnTypes": []
  },
  {
    "ContainingType": "APIBanXeDap.Controllers.TestCheckoutController",
    "Method": "CreateOder",
    "RelativePath": "api/TestCheckout",
    "HttpMethod": "POST",
    "IsController": true,
    "Order": 0,
    "Parameters": [
      {
        "Name": "model",
        "Type": "APIBanXeDap.ViewModels.HoadonVM",
        "IsRequired": true
      }
    ],
    "ReturnTypes": []
  },
  {
    "ContainingType": "APIBanXeDap.Controllers.TestCheckoutController",
    "Method": "CreateDetailOder",
    "RelativePath": "api/TestCheckout/CreateDetailOder",
    "HttpMethod": "POST",
    "IsController": true,
    "Order": 0,
    "Parameters": [
      {
        "Name": "model",
        "Type": "System.Collections.Generic.List\u00601[[APIBanXeDap.ViewModels.ChiTietHoaDonVM, APIBanXeDap, Version=1.0.0.0, Culture=neutral, PublicKeyToken=null]]",
        "IsRequired": true
      }
    ],
    "ReturnTypes": []
  },
  {
    "ContainingType": "APIBanXeDap.Controllers.UpdateProfileController",
    "Method": "Update",
    "RelativePath": "api/UpdateProfile/UpdateProfile/{id}",
    "HttpMethod": "PUT",
    "IsController": true,
    "Order": 0,
    "Parameters": [
      {
        "Name": "id",
        "Type": "System.Int32",
        "IsRequired": true
      },
      {
        "Name": "MaKh",
        "Type": "System.Int32",
        "IsRequired": false
      },
      {
        "Name": "HoTen",
        "Type": "System.String",
        "IsRequired": false
      },
      {
        "Name": "Cccd",
        "Type": "System.String",
        "IsRequired": false
      },
      {
        "Name": "Sdt",
        "Type": "System.String",
        "IsRequired": false
      },
      {
        "Name": "Email",
        "Type": "System.String",
        "IsRequired": false
      },
      {
        "Name": "TenTaiKhoan",
        "Type": "System.String",
        "IsRequired": false
      },
      {
        "Name": "MatKhau",
        "Type": "System.String",
        "IsRequired": false
      },
      {
        "Name": "GioiTinh",
        "Type": "System.String",
        "IsRequired": false
      },
      {
        "Name": "NgaySinh",
        "Type": "System.Nullable\u00601[[System.DateOnly, System.Private.CoreLib, Version=8.0.0.0, Culture=neutral, PublicKeyToken=7cec85d7bea7798e]]",
        "IsRequired": false
      },
      {
        "Name": "DiaChi",
        "Type": "System.String",
        "IsRequired": false
      },
      {
        "Name": "TinhTrang",
        "Type": "System.String",
        "IsRequired": false
      },
      {
        "Name": "Hinh",
        "Type": "System.String",
        "IsRequired": false
      },
      {
        "Name": "Anh",
        "Type": "Microsoft.AspNetCore.Http.IFormFile",
        "IsRequired": false
      },
      {
        "Name": "IsDelete",
        "Type": "System.Nullable\u00601[[System.Boolean, System.Private.CoreLib, Version=8.0.0.0, Culture=neutral, PublicKeyToken=7cec85d7bea7798e]]",
        "IsRequired": false
      }
    ],
    "ReturnTypes": []
  },
  {
    "ContainingType": "APIBanXeDap.Controllers.WishlistController",
    "Method": "ChangeListStatusWishlist",
    "RelativePath": "api/Wishlist/ChangeListStatusWishlist/{idUser}",
    "HttpMethod": "PUT",
    "IsController": true,
    "Order": 0,
    "Parameters": [
      {
        "Name": "idProducts",
        "Type": "System.Int32[]",
        "IsRequired": true
      },
      {
        "Name": "idUser",
        "Type": "System.Int32",
        "IsRequired": true
      }
    ],
    "ReturnTypes": []
  },
  {
    "ContainingType": "APIBanXeDap.Controllers.WishlistController",
    "Method": "ChangeStatusWishlist",
    "RelativePath": "api/Wishlist/ChangeStatusWishlist/{idProduct}\u0026{idUser}",
    "HttpMethod": "PUT",
    "IsController": true,
    "Order": 0,
    "Parameters": [
      {
        "Name": "idProduct",
        "Type": "System.Int32",
        "IsRequired": true
      },
      {
        "Name": "idUser",
        "Type": "System.Int32",
        "IsRequired": true
      }
    ],
    "ReturnTypes": []
  },
  {
    "ContainingType": "APIBanXeDap.Controllers.WishlistController",
    "Method": "CountWishlistOfUser",
    "RelativePath": "api/Wishlist/CountWishlistOfUser/{idUser}",
    "HttpMethod": "GET",
    "IsController": true,
    "Order": 0,
    "Parameters": [
      {
        "Name": "idUser",
        "Type": "System.Int32",
        "IsRequired": true
      }
    ],
    "ReturnTypes": []
  },
  {
    "ContainingType": "APIBanXeDap.Controllers.WishlistController",
    "Method": "GetAllWishlistItems",
    "RelativePath": "api/Wishlist/GetAllWishlistItems/{idUser}",
    "HttpMethod": "GET",
    "IsController": true,
    "Order": 0,
    "Parameters": [
      {
        "Name": "idUser",
        "Type": "System.Int32",
        "IsRequired": true
      }
    ],
    "ReturnTypes": []
  },
  {
    "ContainingType": "APIBanXeDap.Controllers.WishlistController",
    "Method": "GetWishlistItem",
    "RelativePath": "api/Wishlist/GetWishlistItem/{idProduct}\u0026{idUser}",
    "HttpMethod": "GET",
    "IsController": true,
    "Order": 0,
    "Parameters": [
      {
        "Name": "idProduct",
        "Type": "System.Int32",
        "IsRequired": true
      },
      {
        "Name": "idUser",
        "Type": "System.Int32",
        "IsRequired": true
      }
    ],
    "ReturnTypes": []
  },
  {
    "ContainingType": "APIBanXeDap.Controllers.WishlistController",
    "Method": "IsManyInWishlist",
    "RelativePath": "api/Wishlist/IsManyInWishlist/{idUser}",
    "HttpMethod": "GET",
    "IsController": true,
    "Order": 0,
    "Parameters": [
      {
        "Name": "idProducts",
        "Type": "System.Int32[]",
        "IsRequired": true
      },
      {
        "Name": "idUser",
        "Type": "System.Int32",
        "IsRequired": true
      }
    ],
    "ReturnTypes": []
  },
  {
    "ContainingType": "APIBanXeDap.Controllers.WishlistController",
    "Method": "IsOneInWishlist",
    "RelativePath": "api/Wishlist/IsOneInWishlist/{idProduct}\u0026{idUser}",
    "HttpMethod": "GET",
    "IsController": true,
    "Order": 0,
    "Parameters": [
      {
        "Name": "idProduct",
        "Type": "System.Int32",
        "IsRequired": true
      },
      {
        "Name": "idUser",
        "Type": "System.Int32",
        "IsRequired": true
      }
    ],
    "ReturnTypes": []
  },
  {
    "ContainingType": "APIBanXeDap.Controllers.WeatherForecastController",
    "Method": "Get",
    "RelativePath": "WeatherForecast",
    "HttpMethod": "GET",
    "IsController": true,
    "Order": 0,
    "Parameters": [],
    "ReturnTypes": [
      {
        "Type": "System.Collections.Generic.IEnumerable\u00601[[APIBanXeDap.WeatherForecast, APIBanXeDap, Version=1.0.0.0, Culture=neutral, PublicKeyToken=null]]",
        "MediaTypes": [
          "text/plain",
          "application/json",
          "text/json"
        ],
        "StatusCode": 200
      }
    ],
    "EndpointName": "GetWeatherForecast"
  }
]